[
  {
    "team_id": "10350976-91250634",
    "club_id": "10350976",
    "team_code": "",
    "tg": "91250634",
    "tg_seq": 10,
    "competition": "Premier",
    "comp_type": "league",
    "name": "SoHo FC",
    "gp": 11,
    "w": 4,
    "l": 7,
    "d": 0,
    "pts": 12,
    "gf": 22,
    "ga": 33,
    "gd": -11,
    "home_w": 1,
    "home_l": 4,
    "home_d": 0,
    "away_w": 3,
    "away_l": 3,
    "away_d": 0,
    "yellows": "",
    "reds": "",
    "position": 7
  },
  {
    "team_id": "10350991-91250634",
    "club_id": "10350991",
    "team_code": "",
    "tg": "91250634",
    "tg_seq": 10,
    "competition": "Premier",
    "comp_type": "league",
    "name": "BSC Raiders",
    "gp": 10,
    "w": 9,
    "l": 0,
    "d": 1,
    "pts": 28,
    "gf": 31,
    "ga": 5,
    "gd": 26,
    "home_w": 5,
    "home_l": 0,
    "home_d": 0,
    "away_w": 4,
    "away_l": 0,
    "away_d": 1,
    "yellows": "",
    "reds": "",
    "position": 1
  },
  {
    "team_id": "10359005-91250634",
    "club_id": "10359005",
    "team_code": "",
    "tg": "91250634",
    "tg_seq": 10,
    "competition": "Premier",
    "comp_type": "league",
    "name": "Clarence",
    "gp": 10,
    "w": 3,
    "l": 6,
    "d": 1,
    "pts": 10,
    "gf": 23,
    "ga": 25,
    "gd": -2,
    "home_w": 2,
    "home_l": 1,
    "home_d": 1,
    "away_w": 1,
    "away_l": 5,
    "away_d": 0,
    "yellows": "",
    "reds": "",
    "position": 10
  },
  {
    "team_id": "10359017-91250634",
    "club_id": "10359017",
    "team_code": "",
    "tg": "91250634",
    "tg_seq": 10,
    "competition": "Premier",
    "comp_type": "league",
    "name": "Celtic United",
    "gp": 11,
    "w": 3,
    "l": 6,
    "d": 2,
    "pts": 11,
    "gf": 25,
    "ga": 29,
    "gd": -4,
    "home_w": 2,
    "home_l": 2,
    "home_d": 1,
    "away_w": 1,
    "away_l": 4,
    "away_d": 1,
    "yellows": "",
    "reds": "",
    "position": 8
  },
  {
    "team_id": "10359035-91250634",
    "club_id": "10359035",
    "team_code": "",
    "tg": "91250634",
    "tg_seq": 10,
    "competition": "Premier",
    "comp_type": "league",
    "name": "Queenston FC",
    "gp": 11,
    "w": 6,
    "l": 2,
    "d": 3,
    "pts": 21,
    "gf": 28,
    "ga": 18,
    "gd": 10,
    "home_w": 4,
    "home_l": 1,
    "home_d": 1,
    "away_w": 2,
    "away_l": 1,
    "away_d": 2,
    "yellows": "",
    "reds": "",
    "position": 4
  },
  {
    "team_id": "10359050-91250634",
    "club_id": "10359050",
    "team_code": "",
    "tg": "91250634",
    "tg_seq": 10,
    "competition": "Premier",
    "comp_type": "league",
    "name": "Lackawanna FCY",
    "gp": 11,
    "w": 6,
    "l": 3,
    "d": 2,
    "pts": 20,
    "gf": 48,
    "ga": 33,
    "gd": 15,
    "home_w": 4,
    "home_l": 0,
    "home_d": 1,
    "away_w": 2,
    "away_l": 3,
    "away_d": 1,
    "yellows": "",
    "reds": "",
    "position": 5
  },
  {
    "team_id": "18647016-91250634",
    "club_id": "18647016",
    "team_code": "",
    "tg": "91250634",
    "tg_seq": 10,
    "competition": "Premier",
    "comp_type": "league",
    "name": "Buffalo United SS",
    "gp": 11,
    "w": 7,
    "l": 2,
    "d": 2,
    "pts": 23,
    "gf": 32,
    "ga": 15,
    "gd": 17,
    "home_w": 5,
    "home_l": 1,
    "home_d": 0,
    "away_w": 2,
    "away_l": 1,
    "away_d": 2,
    "yellows": "",
    "reds": "",
    "position": 3
  },
  {
    "team_id": "26895907-91250634",
    "club_id": "26895907",
    "team_code": "",
    "tg": "91250634",
    "tg_seq": 10,
    "competition": "Premier",
    "comp_type": "league",
    "name": "Amherst Sharpshooters",
    "gp": 11,
    "w": 8,
    "l": 1,
    "d": 2,
    "pts": 26,
    "gf": 34,
    "ga": 15,
    "gd": 19,
    "home_w": 3,
    "home_l": 0,
    "home_d": 2,
    "away_w": 5,
    "away_l": 1,
    "away_d": 0,
    "yellows": "",
    "reds": "",
    "position": 2
  },
  {
    "team_id": "67527661-91250634",
    "club_id": "67527661",
    "team_code": "",
    "tg": "91250634",
    "tg_seq": 10,
    "competition": "Premier",
    "comp_type": "league",
    "name": "East Aurora FC",
    "gp": 11,
    "w": 1,
    "l": 10,
    "d": 0,
    "pts": 3,
    "gf": 11,
    "ga": 45,
    "gd": -34,
    "home_w": 1,
    "home_l": 5,
    "home_d": 0,
    "away_w": 0,
    "away_l": 5,
    "away_d": 0,
    "yellows": "",
    "reds": "",
    "position": 12
  },
  {
    "team_id": "12579600-91250634",
    "club_id": "12579600",
    "team_code": "",
    "tg": "91250634",
    "tg_seq": 10,
    "competition": "Premier",
    "comp_type": "league",
    "name": "Wolves FC",
    "gp": 11,
    "w": 4,
    "l": 5,
    "d": 2,
    "pts": 14,
    "gf": 15,
    "ga": 25,
    "gd": -10,
    "home_w": 2,
    "home_l": 2,
    "home_d": 2,
    "away_w": 2,
    "away_l": 3,
    "away_d": 0,
    "yellows": "",
    "reds": "",
    "position": 6
  },
  {
    "team_id": "59260537-91250634",
    "club_id": "59260537",
    "team_code": "",
    "tg": "91250634",
    "tg_seq": 10,
    "competition": "Premier",
    "comp_type": "league",
    "name": "Southtowns FPFC",
    "gp": 11,
    "w": 3,
    "l": 6,
    "d": 2,
    "pts": 11,
    "gf": 19,
    "ga": 31,
    "gd": -12,
    "home_w": 2,
    "home_l": 4,
    "home_d": 0,
    "away_w": 1,
    "away_l": 2,
    "away_d": 2,
    "yellows": "",
    "reds": "",
    "position": 9
  },
  {
    "team_id": "75479641-91250634",
    "club_id": "75479641",
    "team_code": "",
    "tg": "91250634",
    "tg_seq": 10,
    "competition": "Premier",
    "comp_type": "league",
    "name": "Williamsville Willies",
    "gp": 11,
    "w": 2,
    "l": 8,
    "d": 1,
    "pts": 7,
    "gf": 15,
    "ga": 29,
    "gd": -14,
    "home_w": 2,
    "home_l": 3,
    "home_d": 1,
    "away_w": 0,
    "away_l": 5,
    "away_d": 0,
    "yellows": "",
    "reds": "",
    "position": 11
  },
  {
    "team_id": "10359008-91250638",
    "club_id": "10359008",
    "team_code": "",
    "tg": "91250638",
    "tg_seq": 20,
    "competition": "Championship",
    "comp_type": "league",
    "name": "Roos FC",
    "gp": 11,
    "w": 6,
    "l": 4,
    "d": 1,
    "pts": 19,
    "gf": 14,
    "ga": 20,
    "gd": -6,
    "home_w": 3,
    "home_l": 3,
    "home_d": 0,
    "away_w": 3,
    "away_l": 1,
    "away_d": 1,
    "yellows": "",
    "reds": "",
    "position": 5
  },
  {
    "team_id": "67526770-91250638",
    "club_id": "67526770",
    "team_code": "",
    "tg": "91250638",
    "tg_seq": 20,
    "competition": "Championship",
    "comp_type": "league",
    "name": "Buffalo Bantu",
    "gp": 11,
    "w": 1,
    "l": 9,
    "d": 1,
    "pts": 4,
    "gf": 9,
    "ga": 30,
    "gd": -21,
    "home_w": 1,
    "home_l": 5,
    "home_d": 0,
    "away_w": 0,
    "away_l": 4,
    "away_d": 1,
    "yellows": "",
    "reds": "",
    "position": 11
  },
  {
    "team_id": "10359047-91250638",
    "club_id": "10359047",
    "team_code": "",
    "tg": "91250638",
    "tg_seq": 20,
    "competition": "Championship",
    "comp_type": "league",
    "name": "Inter SC",
    "gp": 11,
    "w": 9,
    "l": 0,
    "d": 2,
    "pts": 29,
    "gf": 34,
    "ga": 9,
    "gd": 25,
    "home_w": 4,
    "home_l": 0,
    "home_d": 1,
    "away_w": 5,
    "away_l": 0,
    "away_d": 1,
    "yellows": "",
    "reds": "",
    "position": 1
  },
  {
    "team_id": "10359074-91250638",
    "club_id": "10359074",
    "team_code": "",
    "tg": "91250638",
    "tg_seq": 20,
    "competition": "Championship",
    "comp_type": "league",
    "name": "Lykan FC",
    "gp": 11,
    "w": 3,
    "l": 6,
    "d": 2,
    "pts": 11,
    "gf": 17,
    "ga": 23,
    "gd": -6,
    "home_w": 2,
    "home_l": 2,
    "home_d": 2,
    "away_w": 1,
    "away_l": 4,
    "away_d": 0,
    "yellows": "",
    "reds": "",
    "position": 8
  },
  {
    "team_id": "10359086-91250638",
    "club_id": "10359086",
    "team_code": "",
    "tg": "91250638",
    "tg_seq": 20,
    "competition": "Championship",
    "comp_type": "league",
    "name": "Rangers",
    "gp": 11,
    "w": 5,
    "l": 5,
    "d": 1,
    "pts": 16,
    "gf": 21,
    "ga": 18,
    "gd": 3,
    "home_w": 2,
    "home_l": 2,
    "home_d": 1,
    "away_w": 3,
    "away_l": 3,
    "away_d": 0,
    "yellows": "",
    "reds": "",
    "position": 6
  },
  {
    "team_id": "15294627-91250638",
    "club_id": "15294627",
    "team_code": "",
    "tg": "91250638",
    "tg_seq": 20,
    "competition": "Championship",
    "comp_type": "league",
    "name": "Niagara FC",
    "gp": 11,
    "w": 7,
    "l": 2,
    "d": 2,
    "pts": 23,
    "gf": 23,
    "ga": 12,
    "gd": 11,
    "home_w": 3,
    "home_l": 1,
    "home_d": 1,
    "away_w": 4,
    "away_l": 1,
    "away_d": 1,
    "yellows": "",
    "reds": "",
    "position": 4
  },
  {
    "team_id": "59261096-91250638",
    "club_id": "59261096",
    "team_code": "",
    "tg": "91250638",
    "tg_seq": 20,
    "competition": "Championship",
    "comp_type": "league",
    "name": "Beast City SC",
    "gp": 11,
    "w": 8,
    "l": 2,
    "d": 1,
    "pts": 25,
    "gf": 36,
    "ga": 21,
    "gd": 15,
    "home_w": 4,
    "home_l": 1,
    "home_d": 0,
    "away_w": 4,
    "away_l": 1,
    "away_d": 1,
    "yellows": "",
    "reds": "",
    "position": 3
  },
  {
    "team_id": "59261105-91250638",
    "club_id": "59261105",
    "team_code": "",
    "tg": "91250638",
    "tg_seq": 20,
    "competition": "Championship",
    "comp_type": "league",
    "name": "Celtic Hoops",
    "gp": 11,
    "w": 3,
    "l": 7,
    "d": 1,
    "pts": 10,
    "gf": 16,
    "ga": 28,
    "gd": -12,
    "home_w": 1,
    "home_l": 5,
    "home_d": 0,
    "away_w": 2,
    "away_l": 2,
    "away_d": 1,
    "yellows": "",
    "reds": "",
    "position": 9
  },
  {
    "team_id": "10359023-91250638",
    "club_id": "10359023",
    "team_code": "",
    "tg": "91250638",
    "tg_seq": 20,
    "competition": "Championship",
    "comp_type": "league",
    "name": "Polonia",
    "gp": 11,
    "w": 3,
    "l": 5,
    "d": 3,
    "pts": 12,
    "gf": 15,
    "ga": 20,
    "gd": -5,
    "home_w": 1,
    "home_l": 4,
    "home_d": 1,
    "away_w": 2,
    "away_l": 1,
    "away_d": 2,
    "yellows": "",
    "reds": "",
    "position": 7
  },
  {
    "team_id": "75159915-91250638",
    "club_id": "75159915",
    "team_code": "",
    "tg": "91250638",
    "tg_seq": 20,
    "competition": "Championship",
    "comp_type": "league",
    "name": "NMB FC",
    "gp": 11,
    "w": 0,
    "l": 8,
    "d": 3,
    "pts": 3,
    "gf": 9,
    "ga": 24,
    "gd": -15,
    "home_w": 0,
    "home_l": 4,
    "home_d": 2,
    "away_w": 0,
    "away_l": 4,
    "away_d": 1,
    "yellows": "",
    "reds": "",
    "position": 12
  },
  {
    "team_id": "75159921-91250638",
    "club_id": "75159921",
    "team_code": "",
    "tg": "91250638",
    "tg_seq": 20,
    "competition": "Championship",
    "comp_type": "league",
    "name": "West Side FC",
    "gp": 11,
    "w": 2,
    "l": 6,
    "d": 3,
    "pts": 9,
    "gf": 13,
    "ga": 19,
    "gd": -6,
    "home_w": 0,
    "home_l": 3,
    "home_d": 2,
    "away_w": 2,
    "away_l": 3,
    "away_d": 1,
    "yellows": "",
    "reds": "",
    "position": 10
  },
  {
    "team_id": "75479650-91250638",
    "club_id": "75479650",
    "team_code": "",
    "tg": "91250638",
    "tg_seq": 20,
    "competition": "Championship",
    "comp_type": "league",
    "name": "Pendleton United FC",
    "gp": 11,
    "w": 9,
    "l": 2,
    "d": 0,
    "pts": 27,
    "gf": 23,
    "ga": 6,
    "gd": 17,
    "home_w": 3,
    "home_l": 2,
    "home_d": 0,
    "away_w": 6,
    "away_l": 0,
    "away_d": 0,
    "yellows": "",
    "reds": "",
    "position": 2
  },
  {
    "team_id": "67527670-91250636",
    "club_id": "67527670",
    "team_code": "",
    "tg": "91250636",
    "tg_seq": 30,
    "competition": "1st Division",
    "comp_type": "league",
    "name": "FC Quake",
    "gp": 11,
    "w": 8,
    "l": 2,
    "d": 1,
    "pts": 25,
    "gf": 23,
    "ga": 12,
    "gd": 11,
    "home_w": 3,
    "home_l": 2,
    "home_d": 1,
    "away_w": 5,
    "away_l": 0,
    "away_d": 0,
    "yellows": "",
    "reds": "",
    "position": 3
  },
  {
    "team_id": "10359038-91250636",
    "club_id": "10359038",
    "team_code": "",
    "tg": "91250636",
    "tg_seq": 30,
    "competition": "1st Division",
    "comp_type": "league",
    "name": "Hamburg FC",
    "gp": 11,
    "w": 2,
    "l": 7,
    "d": 2,
    "pts": 8,
    "gf": 16,
    "ga": 34,
    "gd": -18,
    "home_w": 1,
    "home_l": 2,
    "home_d": 2,
    "away_w": 1,
    "away_l": 5,
    "away_d": 0,
    "yellows": "",
    "reds": "",
    "position": 16
  },
  {
    "team_id": "10359062-91250636",
    "club_id": "10359062",
    "team_code": "",
    "tg": "91250636",
    "tg_seq": 30,
    "competition": "1st Division",
    "comp_type": "league",
    "name": "Tonawanda United",
    "gp": 11,
    "w": 7,
    "l": 3,
    "d": 1,
    "pts": 22,
    "gf": 34,
    "ga": 20,
    "gd": 14,
    "home_w": 3,
    "home_l": 1,
    "home_d": 1,
    "away_w": 4,
    "away_l": 2,
    "away_d": 0,
    "yellows": "",
    "reds": "",
    "position": 5
  },
  {
    "team_id": "26891552-91250636",
    "club_id": "26891552",
    "team_code": "",
    "tg": "91250636",
    "tg_seq": 30,
    "competition": "1st Division",
    "comp_type": "league",
    "name": "Buffalo Celtic",
    "gp": 11,
    "w": 2,
    "l": 6,
    "d": 3,
    "pts": 9,
    "gf": 17,
    "ga": 26,
    "gd": -9,
    "home_w": 2,
    "home_l": 3,
    "home_d": 1,
    "away_w": 0,
    "away_l": 3,
    "away_d": 2,
    "yellows": "",
    "reds": "",
    "position": 15
  },
  {
    "team_id": "26892099-91250636",
    "club_id": "26892099",
    "team_code": "",
    "tg": "91250636",
    "tg_seq": 30,
    "competition": "1st Division",
    "comp_type": "league",
    "name": "Rampart FC",
    "gp": 11,
    "w": 5,
    "l": 3,
    "d": 3,
    "pts": 18,
    "gf": 20,
    "ga": 14,
    "gd": 6,
    "home_w": 3,
    "home_l": 2,
    "home_d": 1,
    "away_w": 2,
    "away_l": 1,
    "away_d": 2,
    "yellows": "",
    "reds": "",
    "position": 8
  },
  {
    "team_id": "45428657-91250636",
    "club_id": "45428657",
    "team_code": "",
    "tg": "91250636",
    "tg_seq": 30,
    "competition": "1st Division",
    "comp_type": "league",
    "name": "Tri Town United",
    "gp": 11,
    "w": 2,
    "l": 9,
    "d": 0,
    "pts": 6,
    "gf": 9,
    "ga": 29,
    "gd": -20,
    "home_w": 2,
    "home_l": 4,
    "home_d": 0,
    "away_w": 0,
    "away_l": 5,
    "away_d": 0,
    "yellows": "",
    "reds": "",
    "position": 18
  },
  {
    "team_id": "59261111-91250636",
    "club_id": "59261111",
    "team_code": "",
    "tg": "91250636",
    "tg_seq": 30,
    "competition": "1st Division",
    "comp_type": "league",
    "name": "Crusaders FC",
    "gp": 11,
    "w": 3,
    "l": 7,
    "d": 1,
    "pts": 10,
    "gf": 20,
    "ga": 30,
    "gd": -10,
    "home_w": 1,
    "home_l": 3,
    "home_d": 1,
    "away_w": 2,
    "away_l": 4,
    "away_d": 0,
    "yellows": "",
    "reds": "",
    "position": 13
  },
  {
    "team_id": "67527667-91250636",
    "club_id": "67527667",
    "team_code": "",
    "tg": "91250636",
    "tg_seq": 30,
    "competition": "1st Division",
    "comp_type": "league",
    "name": "JL Dutch",
    "gp": 11,
    "w": 1,
    "l": 6,
    "d": 4,
    "pts": 7,
    "gf": 17,
    "ga": 30,
    "gd": -13,
    "home_w": 1,
    "home_l": 5,
    "home_d": 0,
    "away_w": 0,
    "away_l": 1,
    "away_d": 4,
    "yellows": "",
    "reds": "",
    "position": 17
  },
  {
    "team_id": "75479668-91250636",
    "club_id": "75479668",
    "team_code": "",
    "tg": "91250636",
    "tg_seq": 30,
    "competition": "1st Division",
    "comp_type": "league",
    "name": "Grand Island FC",
    "gp": 11,
    "w": 6,
    "l": 3,
    "d": 2,
    "pts": 20,
    "gf": 26,
    "ga": 17,
    "gd": 9,
    "home_w": 2,
    "home_l": 3,
    "home_d": 0,
    "away_w": 4,
    "away_l": 0,
    "away_d": 2,
    "yellows": "",
    "reds": "",
    "position": 7
  },
  {
    "team_id": "75479671-91250636",
    "club_id": "75479671",
    "team_code": "",
    "tg": "91250636",
    "tg_seq": 30,
    "competition": "1st Division",
    "comp_type": "league",
    "name": "Great Lakes Africa",
    "gp": 11,
    "w": 3,
    "l": 7,
    "d": 1,
    "pts": 10,
    "gf": 26,
    "ga": 29,
    "gd": -3,
    "home_w": 1,
    "home_l": 4,
    "home_d": 1,
    "away_w": 2,
    "away_l": 3,
    "away_d": 0,
    "yellows": "",
    "reds": "",
    "position": 12
  },
  {
    "team_id": "10359111-91250636",
    "club_id": "10359111",
    "team_code": "",
    "tg": "91250636",
    "tg_seq": 30,
    "competition": "1st Division",
    "comp_type": "league",
    "name": "Crimson SPAL FC",
    "gp": 11,
    "w": 8,
    "l": 3,
    "d": 0,
    "pts": 24,
    "gf": 30,
    "ga": 11,
    "gd": 19,
    "home_w": 2,
    "home_l": 3,
    "home_d": 0,
    "away_w": 6,
    "away_l": 0,
    "away_d": 0,
    "yellows": "",
    "reds": "",
    "position": 4
  },
  {
    "team_id": "10359092-91250636",
    "club_id": "10359092",
    "team_code": "",
    "tg": "91250636",
    "tg_seq": 30,
    "competition": "1st Division",
    "comp_type": "league",
    "name": "Ukraine",
    "gp": 11,
    "w": 4,
    "l": 7,
    "d": 0,
    "pts": 12,
    "gf": 13,
    "ga": 27,
    "gd": -14,
    "home_w": 2,
    "home_l": 4,
    "home_d": 0,
    "away_w": 2,
    "away_l": 3,
    "away_d": 0,
    "yellows": "",
    "reds": "",
    "position": 11
  },
  {
    "team_id": "10359117-91250636",
    "club_id": "10359117",
    "team_code": "",
    "tg": "91250636",
    "tg_seq": 30,
    "competition": "1st Division",
    "comp_type": "league",
    "name": "Dutch United FC",
    "gp": 11,
    "w": 3,
    "l": 4,
    "d": 4,
    "pts": 13,
    "gf": 25,
    "ga": 28,
    "gd": -3,
    "home_w": 2,
    "home_l": 2,
    "home_d": 2,
    "away_w": 1,
    "away_l": 2,
    "away_d": 2,
    "yellows": "",
    "reds": "",
    "position": 10
  },
  {
    "team_id": "75159918-91250636",
    "club_id": "75159918",
    "team_code": "",
    "tg": "91250636",
    "tg_seq": 30,
    "competition": "1st Division",
    "comp_type": "league",
    "name": "Blizzard FC",
    "gp": 11,
    "w": 5,
    "l": 6,
    "d": 0,
    "pts": 15,
    "gf": 19,
    "ga": 26,
    "gd": -7,
    "home_w": 3,
    "home_l": 3,
    "home_d": 0,
    "away_w": 2,
    "away_l": 3,
    "away_d": 0,
    "yellows": "",
    "reds": "",
    "position": 9
  },
  {
    "team_id": "75479674-91250636",
    "club_id": "75479674",
    "team_code": "",
    "tg": "91250636",
    "tg_seq": 30,
    "competition": "1st Division",
    "comp_type": "league",
    "name": "Los Chupacabras",
    "gp": 11,
    "w": 6,
    "l": 3,
    "d": 2,
    "pts": 20,
    "gf": 33,
    "ga": 20,
    "gd": 13,
    "home_w": 1,
    "home_l": 2,
    "home_d": 2,
    "away_w": 5,
    "away_l": 1,
    "away_d": 0,
    "yellows": "",
    "reds": "",
    "position": 6
  },
  {
    "team_id": "75479680-91250636",
    "club_id": "75479680",
    "team_code": "",
    "tg": "91250636",
    "tg_seq": 30,
    "competition": "1st Division",
    "comp_type": "league",
    "name": "Honey Badgers",
    "gp": 11,
    "w": 3,
    "l": 7,
    "d": 1,
    "pts": 10,
    "gf": 15,
    "ga": 29,
    "gd": -14,
    "home_w": 3,
    "home_l": 2,
    "home_d": 0,
    "away_w": 0,
    "away_l": 5,
    "away_d": 1,
    "yellows": "",
    "reds": "",
    "position": 14
  },
  {
    "team_id": "10359080-91250636",
    "club_id": "10359080",
    "team_code": "",
    "tg": "91250636",
    "tg_seq": 30,
    "competition": "1st Division",
    "comp_type": "league",
    "name": "Eclipse",
    "gp": 11,
    "w": 8,
    "l": 2,
    "d": 1,
    "pts": 25,
    "gf": 34,
    "ga": 22,
    "gd": 12,
    "home_w": 2,
    "home_l": 2,
    "home_d": 1,
    "away_w": 6,
    "away_l": 0,
    "away_d": 0,
    "yellows": "",
    "reds": "",
    "position": 2
  },
  {
    "team_id": "75159924-91250637",
    "club_id": "75159924",
    "team_code": "",
    "tg": "91250637",
    "tg_seq": 40,
    "competition": "2nd Division",
    "comp_type": "league",
    "name": "DSC Buffalo",
    "gp": 10,
    "w": 3,
    "l": 6,
    "d": 1,
    "pts": 10,
    "gf": 19,
    "ga": 31,
    "gd": -12,
    "home_w": 2,
    "home_l": 3,
    "home_d": 1,
    "away_w": 1,
    "away_l": 3,
    "away_d": 0,
    "yellows": "",
    "reds": "",
    "position": 14
  },
  {
    "team_id": "10359002-91250637",
    "club_id": "10359002",
    "team_code": "",
    "tg": "91250637",
    "tg_seq": 40,
    "competition": "2nd Division",
    "comp_type": "league",
    "name": "West Seneca Panthers",
    "gp": 11,
    "w": 7,
    "l": 4,
    "d": 0,
    "pts": 21,
    "gf": 27,
    "ga": 12,
    "gd": 15,
    "home_w": 2,
    "home_l": 3,
    "home_d": 0,
    "away_w": 5,
    "away_l": 1,
    "away_d": 0,
    "yellows": "",
    "reds": "",
    "position": 6
  },
  {
    "team_id": "10359077-91250637",
    "club_id": "10359077",
    "team_code": "",
    "tg": "91250637",
    "tg_seq": 40,
    "competition": "2nd Division",
    "comp_type": "league",
    "name": "WNY United Reds",
    "gp": 11,
    "w": 1,
    "l": 9,
    "d": 1,
    "pts": 4,
    "gf": 8,
    "ga": 32,
    "gd": -24,
    "home_w": 0,
    "home_l": 4,
    "home_d": 1,
    "away_w": 1,
    "away_l": 5,
    "away_d": 0,
    "yellows": "",
    "reds": "",
    "position": 18
  },
  {
    "team_id": "35216066-91250637",
    "club_id": "35216066",
    "team_code": "",
    "tg": "91250637",
    "tg_seq": 40,
    "competition": "2nd Division",
    "comp_type": "league",
    "name": "Meerkats FC",
    "gp": 11,
    "w": 0,
    "l": 11,
    "d": 0,
    "pts": 0,
    "gf": 10,
    "ga": 49,
    "gd": -39,
    "home_w": 0,
    "home_l": 6,
    "home_d": 0,
    "away_w": 0,
    "away_l": 5,
    "away_d": 0,
    "yellows": "",
    "reds": "",
    "position": 20
  },
  {
    "team_id": "75159996-91250637",
    "club_id": "75159996",
    "team_code": "",
    "tg": "91250637",
    "tg_seq": 40,
    "competition": "2nd Division",
    "comp_type": "league",
    "name": "FK Bosna",
    "gp": 11,
    "w": 6,
    "l": 4,
    "d": 1,
    "pts": 19,
    "gf": 25,
    "ga": 16,
    "gd": 9,
    "home_w": 3,
    "home_l": 2,
    "home_d": 1,
    "away_w": 3,
    "away_l": 2,
    "away_d": 0,
    "yellows": "",
    "reds": "",
    "position": 11
  },
  {
    "team_id": "75479647-91250637",
    "club_id": "75479647",
    "team_code": "",
    "tg": "91250637",
    "tg_seq": 40,
    "competition": "2nd Division",
    "comp_type": "league",
    "name": "Celtic 1888",
    "gp": 11,
    "w": 9,
    "l": 1,
    "d": 1,
    "pts": 28,
    "gf": 34,
    "ga": 14,
    "gd": 20,
    "home_w": 4,
    "home_l": 1,
    "home_d": 0,
    "away_w": 5,
    "away_l": 0,
    "away_d": 1,
    "yellows": "",
    "reds": "",
    "position": 2
  },
  {
    "team_id": "75479653-91250637",
    "club_id": "75479653",
    "team_code": "",
    "tg": "91250637",
    "tg_seq": 40,
    "competition": "2nd Division",
    "comp_type": "league",
    "name": "Youngstown Marksmen",
    "gp": 11,
    "w": 6,
    "l": 2,
    "d": 3,
    "pts": 21,
    "gf": 26,
    "ga": 12,
    "gd": 14,
    "home_w": 3,
    "home_l": 1,
    "home_d": 2,
    "away_w": 3,
    "away_l": 1,
    "away_d": 1,
    "yellows": "",
    "reds": "",
    "position": 7
  },
  {
    "team_id": "75479662-91250637",
    "club_id": "75479662",
    "team_code": "",
    "tg": "91250637",
    "tg_seq": 40,
    "competition": "2nd Division",
    "comp_type": "league",
    "name": "Celtic Brigade",
    "gp": 11,
    "w": 8,
    "l": 1,
    "d": 2,
    "pts": 26,
    "gf": 40,
    "ga": 16,
    "gd": 24,
    "home_w": 4,
    "home_l": 0,
    "home_d": 1,
    "away_w": 4,
    "away_l": 1,
    "away_d": 1,
    "yellows": "",
    "reds": "",
    "position": 3
  },
  {
    "team_id": "75479677-91250637",
    "club_id": "75479677",
    "team_code": "",
    "tg": "91250637",
    "tg_seq": 40,
    "competition": "2nd Division",
    "comp_type": "league",
    "name": "Kingsmen SC",
    "gp": 11,
    "w": 3,
    "l": 8,
    "d": 0,
    "pts": 9,
    "gf": 25,
    "ga": 35,
    "gd": -10,
    "home_w": 2,
    "home_l": 4,
    "home_d": 0,
    "away_w": 1,
    "away_l": 4,
    "away_d": 0,
    "yellows": "",
    "reds": "",
    "position": 15
  },
  {
    "team_id": "75479686-91250637",
    "club_id": "75479686",
    "team_code": "",
    "tg": "91250637",
    "tg_seq": 40,
    "competition": "2nd Division",
    "comp_type": "league",
    "name": "Queen City Pride",
    "gp": 10,
    "w": 4,
    "l": 5,
    "d": 1,
    "pts": 13,
    "gf": 32,
    "ga": 32,
    "gd": 0,
    "home_w": 2,
    "home_l": 2,
    "home_d": 1,
    "away_w": 2,
    "away_l": 3,
    "away_d": 0,
    "yellows": "",
    "reds": "",
    "position": 12
  },
  {
    "team_id": "75479689-91250637",
    "club_id": "75479689",
    "team_code": "",
    "tg": "91250637",
    "tg_seq": 40,
    "competition": "2nd Division",
    "comp_type": "league",
    "name": "Delco Academy",
    "gp": 11,
    "w": 4,
    "l": 6,
    "d": 1,
    "pts": 13,
    "gf": 12,
    "ga": 18,
    "gd": -6,
    "home_w": 0,
    "home_l": 4,
    "home_d": 1,
    "away_w": 4,
    "away_l": 2,
    "away_d": 0,
    "yellows": "",
    "reds": "",
    "position": 13
  },
  {
    "team_id": "12579571-91250637",
    "club_id": "12579571",
    "team_code": "",
    "tg": "91250637",
    "tg_seq": 40,
    "competition": "2nd Division",
    "comp_type": "league",
    "name": "Devils",
    "gp": 11,
    "w": 7,
    "l": 4,
    "d": 0,
    "pts": 21,
    "gf": 23,
    "ga": 16,
    "gd": 7,
    "home_w": 3,
    "home_l": 2,
    "home_d": 0,
    "away_w": 4,
    "away_l": 2,
    "away_d": 0,
    "yellows": "",
    "reds": "",
    "position": 8
  },
  {
    "team_id": "75159990-91250637",
    "club_id": "75159990",
    "team_code": "",
    "tg": "91250637",
    "tg_seq": 40,
    "competition": "2nd Division",
    "comp_type": "league",
    "name": "Great White Buffalo",
    "gp": 11,
    "w": 6,
    "l": 2,
    "d": 3,
    "pts": 21,
    "gf": 21,
    "ga": 15,
    "gd": 6,
    "home_w": 4,
    "home_l": 1,
    "home_d": 1,
    "away_w": 2,
    "away_l": 1,
    "away_d": 2,
    "yellows": "",
    "reds": "",
    "position": 9
  },
  {
    "team_id": "75159993-91250637",
    "club_id": "75159993",
    "team_code": "",
    "tg": "91250637",
    "tg_seq": 40,
    "competition": "2nd Division",
    "comp_type": "league",
    "name": "Revolution SC",
    "gp": 11,
    "w": 6,
    "l": 3,
    "d": 2,
    "pts": 20,
    "gf": 27,
    "ga": 19,
    "gd": 8,
    "home_w": 4,
    "home_l": 0,
    "home_d": 2,
    "away_w": 2,
    "away_l": 3,
    "away_d": 0,
    "yellows": "",
    "reds": "",
    "position": 10
  },
  {
    "team_id": "10359105-91250640",
    "club_id": "10359105",
    "team_code": "",
    "tg": "91250640",
    "tg_seq": 60,
    "competition": "Over 35",
    "comp_type": "over35",
    "name": "C.S. Italia",
    "gp": 10,
    "w": 2,
    "l": 8,
    "d": 0,
    "pts": 6,
    "gf": 13,
    "ga": 50,
    "gd": -37,
    "home_w": 1,
    "home_l": 5,
    "home_d": 0,
    "away_w": 1,
    "away_l": 3,
    "away_d": 0,
    "yellows": "",
    "reds": "",
    "position": 6
  },
  {
    "team_id": "46512663-91250640",
    "club_id": "46512663",
    "team_code": "",
    "tg": "91250640",
    "tg_seq": 60,
    "competition": "Over 35",
    "comp_type": "over35",
    "name": "Azzurri",
    "gp": 10,
    "w": 5,
    "l": 4,
    "d": 1,
    "pts": 16,
    "gf": 23,
    "ga": 22,
    "gd": 1,
    "home_w": 1,
    "home_l": 4,
    "home_d": 0,
    "away_w": 4,
    "away_l": 0,
    "away_d": 1,
    "yellows": "",
    "reds": "",
    "position": 4
  },
  {
    "team_id": "46512666-91250640",
    "club_id": "46512666",
    "team_code": "",
    "tg": "91250640",
    "tg_seq": 60,
    "competition": "Over 35",
    "comp_type": "over35",
    "name": "Aliens",
    "gp": 10,
    "w": 7,
    "l": 3,
    "d": 0,
    "pts": 21,
    "gf": 46,
    "ga": 19,
    "gd": 27,
    "home_w": 2,
    "home_l": 2,
    "home_d": 0,
    "away_w": 5,
    "away_l": 1,
    "away_d": 0,
    "yellows": "",
    "reds": "",
    "position": 2
  },
  {
    "team_id": "46512669-91250640",
    "club_id": "46512669",
    "team_code": "",
    "tg": "91250640",
    "tg_seq": 60,
    "competition": "Over 35",
    "comp_type": "over35",
    "name": "Oranje",
    "gp": 10,
    "w": 1,
    "l": 9,
    "d": 0,
    "pts": 3,
    "gf": 14,
    "ga": 55,
    "gd": -41,
    "home_w": 1,
    "home_l": 3,
    "home_d": 0,
    "away_w": 0,
    "away_l": 6,
    "away_d": 0,
    "yellows": "",
    "reds": "",
    "position": 7
  },
  {
    "team_id": "46512672-91250640",
    "club_id": "46512672",
    "team_code": "",
    "tg": "91250640",
    "tg_seq": 60,
    "competition": "Over 35",
    "comp_type": "over35",
    "name": "Bluestars FC",
    "gp": 10,
    "w": 8,
    "l": 2,
    "d": 0,
    "pts": 24,
    "gf": 47,
    "ga": 15,
    "gd": 32,
    "home_w": 4,
    "home_l": 2,
    "home_d": 0,
    "away_w": 4,
    "away_l": 0,
    "away_d": 0,
    "yellows": "",
    "reds": "",
    "position": 1
  },
  {
    "team_id": "46512675-91250640",
    "club_id": "46512675",
    "team_code": "",
    "tg": "91250640",
    "tg_seq": 60,
    "competition": "Over 35",
    "comp_type": "over35",
    "name": "West United FC",
    "gp": 10,
    "w": 6,
    "l": 3,
    "d": 1,
    "pts": 19,
    "gf": 32,
    "ga": 14,
    "gd": 18,
    "home_w": 2,
    "home_l": 2,
    "home_d": 1,
    "away_w": 4,
    "away_l": 1,
    "away_d": 0,
    "yellows": "",
    "reds": "",
    "position": 3
  },
  {
    "team_id": "31566782-91250639",
    "club_id": "31566782",
    "team_code": "",
    "tg": "91250639",
    "tg_seq": 50,
    "competition": "3rd Division",
    "comp_type": "league",
    "name": "Rust Belt United",
    "gp": 11,
    "w": 0,
    "l": 10,
    "d": 1,
    "pts": 1,
    "gf": 8,
    "ga": 43,
    "gd": -35,
    "home_w": 0,
    "home_l": 5,
    "home_d": 0,
    "away_w": 0,
    "away_l": 5,
    "away_d": 1,
    "yellows": "",
    "reds": "",
    "position": 12
  },
  {
    "team_id": "59262126-91250639",
    "club_id": "59262126",
    "team_code": "",
    "tg": "91250639",
    "tg_seq": 50,
    "competition": "3rd Division",
    "comp_type": "league",
    "name": "Celtic Classic",
    "gp": 11,
    "w": 2,
    "l": 6,
    "d": 3,
    "pts": 9,
    "gf": 21,
    "ga": 40,
    "gd": -19,
    "home_w": 1,
    "home_l": 2,
    "home_d": 3,
    "away_w": 1,
    "away_l": 4,
    "away_d": 0,
    "yellows": "",
    "reds": "",
    "position": 10
  },
  {
    "team_id": "75479659-91250639",
    "club_id": "75479659",
    "team_code": "",
    "tg": "91250639",
    "tg_seq": 50,
    "competition": "3rd Division",
    "comp_type": "league",
    "name": "Bangarang FC",
    "gp": 11,
    "w": 2,
    "l": 6,
    "d": 3,
    "pts": 9,
    "gf": 25,
    "ga": 40,
    "gd": -15,
    "home_w": 0,
    "home_l": 3,
    "home_d": 2,
    "away_w": 2,
    "away_l": 3,
    "away_d": 1,
    "yellows": "",
    "reds": "",
    "position": 8
  },
  {
    "team_id": "75479683-91250639",
    "club_id": "75479683",
    "team_code": "",
    "tg": "91250639",
    "tg_seq": 50,
    "competition": "3rd Division",
    "comp_type": "league",
    "name": "North Buffalo FCR",
    "gp": 11,
    "w": 3,
    "l": 4,
    "d": 4,
    "pts": 13,
    "gf": 16,
    "ga": 22,
    "gd": -6,
    "home_w": 3,
    "home_l": 1,
    "home_d": 1,
    "away_w": 0,
    "away_l": 3,
    "away_d": 3,
    "yellows": "",
    "reds": "",
    "position": 7
  },
  {
    "team_id": "75479695-91250639",
    "club_id": "75479695",
    "team_code": "",
    "tg": "91250639",
    "tg_seq": 50,
    "competition": "3rd Division",
    "comp_type": "league",
    "name": "Big Green SC",
    "gp": 11,
    "w": 4,
    "l": 5,
    "d": 2,
    "pts": 14,
    "gf": 24,
    "ga": 24,
    "gd": 0,
    "home_w": 1,
    "home_l": 3,
    "home_d": 2,
    "away_w": 3,
    "away_l": 2,
    "away_d": 0,
    "yellows": "",
    "reds": "",
    "position": 6
  },
  {
    "team_id": "87153546-91250639",
    "club_id": "87153546",
    "team_code": "",
    "tg": "91250639",
    "tg_seq": 50,
    "competition": "3rd Division",
    "comp_type": "league",
    "name": "Tesla FC",
    "gp": 11,
    "w": 9,
    "l": 2,
    "d": 0,
    "pts": 27,
    "gf": 35,
    "ga": 12,
    "gd": 23,
    "home_w": 6,
    "home_l": 0,
    "home_d": 0,
    "away_w": 3,
    "away_l": 2,
    "away_d": 0,
    "yellows": "",
    "reds": "",
    "position": 2
  },
  {
    "team_id": "75479665-91250639",
    "club_id": "75479665",
    "team_code": "",
    "tg": "91250639",
    "tg_seq": 50,
    "competition": "3rd Division",
    "comp_type": "league",
    "name": "Lasalle FC",
    "gp": 11,
    "w": 9,
    "l": 2,
    "d": 0,
    "pts": 27,
    "gf": 28,
    "ga": 10,
    "gd": 18,
    "home_w": 4,
    "home_l": 2,
    "home_d": 0,
    "away_w": 5,
    "away_l": 0,
    "away_d": 0,
    "yellows": "",
    "reds": "",
    "position": 3
  },
  {
    "team_id": "10359123-91250639",
    "club_id": "10359123",
    "team_code": "",
    "tg": "91250639",
    "tg_seq": 50,
    "competition": "3rd Division",
    "comp_type": "league",
    "name": "Cheektowaga White Eagles",
    "gp": 11,
    "w": 2,
    "l": 9,
    "d": 0,
    "pts": 6,
    "gf": 15,
    "ga": 34,
    "gd": -19,
    "home_w": 1,
    "home_l": 5,
    "home_d": 0,
    "away_w": 1,
    "away_l": 4,
    "away_d": 0,
    "yellows": "",
    "reds": "",
    "position": 11
  },
  {
    "team_id": "67526452-91250637",
    "club_id": "67526452",
    "team_code": "",
    "tg": "91250637",
    "tg_seq": 40,
    "competition": "2nd Division",
    "comp_type": "league",
    "name": "West Seneca FC",
    "gp": 11,
    "w": 7,
    "l": 2,
    "d": 2,
    "pts": 23,
    "gf": 25,
    "ga": 12,
    "gd": 13,
    "home_w": 3,
    "home_l": 1,
    "home_d": 1,
    "away_w": 4,
    "away_l": 1,
    "away_d": 1,
    "yellows": "",
    "reds": "",
    "position": 4
  },
  {
    "team_id": "91256977-91250637",
    "club_id": "91256977",
    "team_code": "",
    "tg": "91250637",
    "tg_seq": 40,
    "competition": "2nd Division",
    "comp_type": "league",
    "name": "Lykan United",
    "gp": 11,
    "w": 7,
    "l": 3,
    "d": 1,
    "pts": 22,
    "gf": 23,
    "ga": 11,
    "gd": 12,
    "home_w": 4,
    "home_l": 1,
    "home_d": 0,
    "away_w": 3,
    "away_l": 2,
    "away_d": 1,
    "yellows": "",
    "reds": "",
    "position": 5
  },
  {
    "team_id": "91256980-91250637",
    "club_id": "91256980",
    "team_code": "",
    "tg": "91250637",
    "tg_seq": 40,
    "competition": "2nd Division",
    "comp_type": "league",
    "name": "Olean 1854 FC",
    "gp": 11,
    "w": 9,
    "l": 1,
    "d": 1,
    "pts": 28,
    "gf": 45,
    "ga": 7,
    "gd": 38,
    "home_w": 5,
    "home_l": 0,
    "home_d": 0,
    "away_w": 4,
    "away_l": 1,
    "away_d": 1,
    "yellows": "",
    "reds": "",
    "position": 1
  },
  {
    "team_id": "91256984-91250637",
    "club_id": "91256984",
    "team_code": "",
    "tg": "91250637",
    "tg_seq": 40,
    "competition": "2nd Division",
    "comp_type": "league",
    "name": "11 Stars FC",
    "gp": 11,
    "w": 0,
    "l": 10,
    "d": 1,
    "pts": 1,
    "gf": 7,
    "ga": 38,
    "gd": -31,
    "home_w": 0,
    "home_l": 4,
    "home_d": 1,
    "away_w": 0,
    "away_l": 6,
    "away_d": 0,
    "yellows": "",
    "reds": "",
    "position": 19
  },
  {
    "team_id": "91256987-91250637",
    "club_id": "91256987",
    "team_code": "",
    "tg": "91250637",
    "tg_seq": 40,
    "competition": "2nd Division",
    "comp_type": "league",
    "name": "Clarence Rebels",
    "gp": 11,
    "w": 1,
    "l": 8,
    "d": 2,
    "pts": 5,
    "gf": 12,
    "ga": 41,
    "gd": -29,
    "home_w": 1,
    "home_l": 5,
    "home_d": 0,
    "away_w": 0,
    "away_l": 3,
    "away_d": 2,
    "yellows": "",
    "reds": "",
    "position": 17
  },
  {
    "team_id": "91257538-91250639",
    "club_id": "91257538",
    "team_code": "",
    "tg": "91250639",
    "tg_seq": 50,
    "competition": "3rd Division",
    "comp_type": "league",
    "name": "Medina Mustangs FC",
    "gp": 11,
    "w": 9,
    "l": 1,
    "d": 1,
    "pts": 28,
    "gf": 43,
    "ga": 7,
    "gd": 36,
    "home_w": 5,
    "home_l": 0,
    "home_d": 0,
    "away_w": 4,
    "away_l": 1,
    "away_d": 1,
    "yellows": "",
    "reds": "",
    "position": 1
  },
  {
    "team_id": "91257544-91250639",
    "club_id": "91257544",
    "team_code": "",
    "tg": "91250639",
    "tg_seq": 50,
    "competition": "3rd Division",
    "comp_type": "league",
    "name": "NY Elite",
    "gp": 11,
    "w": 8,
    "l": 3,
    "d": 0,
    "pts": 24,
    "gf": 40,
    "ga": 12,
    "gd": 28,
    "home_w": 3,
    "home_l": 2,
    "home_d": 0,
    "away_w": 5,
    "away_l": 1,
    "away_d": 0,
    "yellows": "",
    "reds": "",
    "position": 4
  },
  {
    "team_id": "91257643-91250639",
    "club_id": "91257643",
    "team_code": "",
    "tg": "91250639",
    "tg_seq": 50,
    "competition": "3rd Division",
    "comp_type": "league",
    "name": "Iron Lungz FC",
    "gp": 11,
    "w": 2,
    "l": 6,
    "d": 3,
    "pts": 9,
    "gf": 16,
    "ga": 33,
    "gd": -17,
    "home_w": 1,
    "home_l": 3,
    "home_d": 1,
    "away_w": 1,
    "away_l": 3,
    "away_d": 2,
    "yellows": "",
    "reds": "",
    "position": 9
  },
  {
    "team_id": "75159801-91250636",
    "club_id": "75159801",
    "team_code": "",
    "tg": "91250636",
    "tg_seq": 30,
    "competition": "1st Division",
    "comp_type": "league",
    "name": "OP Alliance",
    "gp": 11,
    "w": 10,
    "l": 1,
    "d": 0,
    "pts": 30,
    "gf": 35,
    "ga": 8,
    "gd": 27,
    "home_w": 5,
    "home_l": 0,
    "home_d": 0,
    "away_w": 5,
    "away_l": 1,
    "away_d": 0,
    "yellows": "",
    "reds": "",
    "position": 1
  },
  {
    "team_id": "62886844-91250637",
    "club_id": "62886844",
    "team_code": "",
    "tg": "91250637",
    "tg_seq": 40,
    "competition": "2nd Division",
    "comp_type": "league",
    "name": "Sahara Gunners",
    "gp": 11,
    "w": 2,
    "l": 6,
    "d": 3,
    "pts": 9,
    "gf": 19,
    "ga": 34,
    "gd": -15,
    "home_w": 1,
    "home_l": 5,
    "home_d": 0,
    "away_w": 1,
    "away_l": 1,
    "away_d": 3,
    "yellows": "",
    "reds": "",
    "position": 16
  },
  {
    "team_id": "87153543-91250639",
    "club_id": "87153543",
    "team_code": "",
    "tg": "91250639",
    "tg_seq": 50,
    "competition": "3rd Division",
    "comp_type": "league",
    "name": "Moby Ducks FC",
    "gp": 11,
    "w": 7,
    "l": 3,
    "d": 1,
    "pts": 22,
    "gf": 23,
    "ga": 17,
    "gd": 6,
    "home_w": 4,
    "home_l": 2,
    "home_d": 0,
    "away_w": 3,
    "away_l": 1,
    "away_d": 1,
    "yellows": "",
    "reds": "",
    "position": 5
  },
  {
    "team_id": "91327989-91250640",
    "club_id": "91327989",
    "team_code": "",
    "tg": "91250640",
    "tg_seq": 60,
    "competition": "Over 35",
    "comp_type": "over35",
    "name": "Aztecas FC",
    "gp": 10,
    "w": 5,
    "l": 5,
    "d": 0,
    "pts": 15,
    "gf": 30,
    "ga": 30,
    "gd": 0,
    "home_w": 2,
    "home_l": 3,
    "home_d": 0,
    "away_w": 3,
    "away_l": 2,
    "away_d": 0,
    "yellows": "",
    "reds": "",
    "position": 5
  }
]